applecrate/__init__.py
applecrate/__main__.py
applecrate/build.py
applecrate/cli.py
applecrate/pkgutil.py
applecrate/selfupdate.py
applecrate/template_utils.py
applecrate/utils.py
applecrate/version.py
applecrate/templates/Distribution
applecrate/templates/README.md
applecrate/templates/conclusion.md
applecrate/templates/postinstall
applecrate/templates/preinstall
applecrate/templates/uninstall.sh
applecrate/templates/welcome.md
applecrate-0.2.0.dist-info/entry_points.txt
applecrate-0.2.0.dist-info/LICENSE
applecrate-0.2.0.dist-info/WHEEL
applecrate-0.2.0.dist-info/METADATA
applecrate-0.2.0.dist-info/RECORD
