Metadata-Version: 2.1
Name: applecrate
Version: 0.2.0
Summary: applecrate: A Python package for creating macOS installer packages.
Author-email: Rhet Turnbull <rturnbull+git@gmail.com>
Classifier: License :: OSI Approved :: Apache Software License
Requires-Dist: Jinja2>=3.1.3
Requires-Dist: click>=8.1.7
Requires-Dist: markdown2>=2.4.12
Requires-Dist: packaging>=23.2
Requires-Dist: pip>=24.0
Requires-Dist: toml>=0.10.2
Requires-Dist: bump2version>=1.0.1,<2.0.0 ; extra == "dev"
Requires-Dist: cogapp>=3.3.0,<4.0.0 ; extra == "dev"
Requires-Dist: mypy>=1.8.0 ; extra == "dev"
Requires-Dist: types-toml ; extra == "dev"
Requires-Dist: mkdocs>=1.4.2 ; extra == "docs"
Requires-Dist: mkdocs-material>=9.0.13 ; extra == "docs"
Requires-Dist: mkdocstrings-python>=0.8.3 ; extra == "docs"
Requires-Dist: ruff>=0.1.14 ; extra == "lint"
Requires-Dist: pytest>=7.4.2 ; extra == "test"
Requires-Dist: pytest-cov ; extra == "test"
Requires-Dist: mypy>=1.8.0 ; extra == "test"
Project-URL: Home, https://github.com/RhetTbull/applecrate
Project-URL: Issues, https://github.com/RhetTbull/applecrate/issues
Project-URL: Source, https://github.com/RhetTbull/applecrate
Provides-Extra: dev
Provides-Extra: docs
Provides-Extra: lint
Provides-Extra: test
